{
  "filename": "ten_questions_about_human_error_3.docx",
  "metadata": {
    "title": "Ten Questions  About Human Error: A New View Of Human Factors And System Safety Chapter 3",
    "author(s)": "Sidney W. A. Dekker",
    "tags": "human, error, factors, accident"
  },
  "category": "safety",
  "chunks": [
    {
      "chunk_id": "ten_questions_about_human_error_3.docx_0",
      "text": "title questions human view human factors system safety chapter author sidney category analysis human factors errors tags human factor accident doctor dangerous owner physician united states institute medicine estimate year people result medical error corrigan donaldson make yearly accidental death rate doctor word seven doctor patient year mistake take owner contrast owner united states error lead accidental death year mean accidental death rate cause owner owner year owner somebody mistake doctor time likely somebody mistake everybody everybody doctor several doctor thus severely pose human problem organization stakeholder trade industry group regulator safety health operation count tabulate error appear meaningful measure provide immediate numeric estimate probability accidental death injury undesirable event also allow comparison system component hospital hospital airline aircraft fleet pilot route route keep track adverse event think provide easy quick accurate access internal safety working moreover adverse event start reason deep probe order search environmental threat favor able condition could change prevent recurrence course also sheer scientific curiosity try understand different type adverse event different type error categorize fundamental science since modern time past decade transportation human factor endeavor quantify safety problem find potential source vulnerability fail spawn number classification system classify decision error together condition help produce specific goal example categorize information transfer problem instruction error watch change briefing ordination failure other divide cause cognitive social situational physical environmental ergonomic factor other tempt classify cause along line linear information processing decision make model apply cheese metaphor system multiple layer defense hole identification error vulnerabilitie causal chain classification system use event dent investigation observation current human performance measure know pursue categorization tabulation error human factor make number assumption take certain philosophical position little make explicit description method carry sequence utility quality count measure safety health directing resource improvement example method observer ask distinguish tween procedure error proficiency error proficiency error relate lack skill experience recent practice whereas dure error occur carry prescribe normative sequence action checklist straightforward croft report follow problem confront observer type pilot enter wrong altitude flight computer gitim either category count method procedural proficiency example enter wrong flight altitude flight management system consider dural know certain automate feature aircraft flight computer consider proficiency pilot enter wrong flight altitude flight management procedural proficiency issue categorize thomas kuhn encourage science turn creative",
      "tokens": 396
    },
    {
      "chunk_id": "ten_questions_about_human_error_3.docx_1",
      "text": "philosophy confront inkling problem relate observation problem categorize observation theoretical class effective elucidate necessary weaken grip tradition collective mind suggest basis certainly appropriate epistemological question arise question know think know understand classification problem associate engage brief analysis contemporary philo tradition govern human factor research worldview take place realism errors exist discover method position human factor take observational tool error realist presume real objective world verifiable pattern observe categorize predict error kind durkheim fact emile durkheim found father sociology believe social reality objectively available neutral impartial empirical scrutiny reality exist truth worth strive course obstacle get truth reality hard pursue close mapping correspondence reality valid legitimate goal theory develop ment goal achieve close mapping reality govern count method difficulty get corre difficulty merely methodological nature difficulty refinement observational instrument ional training observer presumption modernist inherit enlightened idea scientific revolution fine scientific spirit method call direct searchlight across empirical reality method call correct ambiguity observation method call break open portion hitherto unexplored empirical reality bring focus portion vague elusive label approach empirical reality could include positivism hold type knowledge worth bother base directly experience positivism soci doctrine auguste comte highest pure true form knowledge simple description sensory noman word observer example pilot fail spoiler write categorize positivist obtain negative connotation really mean come social science research instead neutral describing position counting method realist naively operate realist stance researcher concern validity measure correspondence reliability reality capture describe objectively outside observer also possible generate converging evidence multiple observer consequently achieve agreement nature reality mean reliability reliable contact make empirical reality generate equal access return across observation observer count method rely possible tabulate error different observer different observation different flight line build common database use kind norm exist entrant measure absolute objectivity impossible obtain world messy phenomenon occur empirical world confound method forever imperfect come surprise count method different definition different level definition messy confound phenomenon cause failure example pilot failure spoiler runway overrun failure classification rely definition categorize kind observable error operator make sion error perceptual error skill base error probe cause failure processing perform ance",
      "tokens": 386
    },
    {
      "chunk_id": "ten_questions_about_human_error_3.docx_2",
      "text": "accord helm reich error result physiological psychological limitation human cause include fatigue workload fear cognitive overload interpersonal muni cation imperfect information processing flawed decision process specifically departure kind standard standard consist operating procedure violation whether exceptional routine intentional unintentional helm reich example accord process definition depend standard observer course come different conclusion differentiate among different possible definition know problem cause consequence counting method causal confound messiness neither really surprising really problematic truth elusive get method right method solve problem method course really problem method modernist would would stock answer revolution onward methodological wrestling empirical reality empirical reality play hard catch prove pretty game methodological find well method problem empirical reality swim view unadulterate really happen postmodernist would argue something different single stable reality approach good method describe term correspondence reality exist describe reality particular procedure imply type mapping objectively attainable external reality close remote postmodernist deal referential describe phenomenon though reflect represent thing stable objective something rather capture bing phenomenon result collective generation agree ment mean case human factor researcher industrial counterpart reach reality procedure word socially construct shaped dependent paradigms knowledge evolve group con meaning enforce hand system server training label communication result industry acceptance promotion philosopher like kuhn point paradigm language think point adopt kind self sustain energy consensus authority angell strau human factor auditor count error manager scientific measure presume error exist order prove error exist auditor measure word measure error become proof existence existence preordain measurement everyone agree count error step forward safety almost everyone agree step forward practice question question postmodernist would argue procedural become true appear people close corre objective reality community specialist contribute development tool make appear agree language make visible nothing rent true accept utility count likely industry accept theory reality validity observation generate authority author teach text evidence headline croft announce researcher perfect way monitor pilot form ance cockpit researcher perfect little industry accept authority alternative kuhn competence postmodernism reality observe procedure settlement among informed participant postmodernism go beyond common denominator realism product pani ment scientific revolution assume common denominator find system belief value strive converge common denominator scientific meth truth worth look method postmodernism contrast condition cope without",
      "tokens": 398
    },
    {
      "chunk_id": "ten_questions_about_human_error_3.docx_3",
      "text": "denominator accord postmodernism belief lief procedural construction contaminate encounter representation objective empirical reality postmodernism challenge entire modernist culture realism empiricism count method stance postmodernist defiance appear critique counting also reverberate throughout university especially science capra never come unscathed however word thompson suffer carte anxiety idea fix stable reality round independent look give idea would descend uncertainty idealism subjectivism would ground long predetermine norm stan dard constantly shift chaos individual impression lead lativi ultimately nihilism closing debate anxiety possible ask position real modernist postmodernist capitulate naive realism assume reality approximate well either modernist postmodernist depend make argument although people live empirical world actually hard core constructionist would thing arrive rather different equally valid conclusion go inside propose different vocabulary model capture phenomena tie philosopher sometimes example though first sight objective stable entity external reality separate observer mean entirely different thing someone log industry compare wanderer sahara inter preta ion valid validity measure term local vance situational applicability social acceptability term correspondence real external world among different character ion world real true validity function interpretation conform worldview server make appeal procedure legitimate acceptable form capture empirical encounter consensual system like minded coder consumer together agree stic label appeal fall fertile ground validity observation negotiable depend appeal go look listen known ontological lativi flexibility uncertainty mean world particular situation ontological submit mean observe particular situation depend entirely observer bring source shade sustenance survival follow kant idea social embrace common experience observe perceive object include human passive receiving process active engage observer much change affect serve lativi create epistemological uncertainty counting method attempt shoehorn observation numerical objectivity social observer coder feel uncertainty time another procedure proficiency perhaps cause consequence kant feel uncertainty would serve indication particularly obtuse server would certainly proof epistemological astuteness either method counter uncertainty suffer epistemological realize certainty know know whether know reach within rule paradigm stock answer challenge whenever confront problem bring serva ion theory close correspondence methodological agree ment refinement include observer train standardization close",
      "tokens": 390
    },
    {
      "chunk_id": "ten_questions_about_human_error_3.docx_4",
      "text": "uncertainty well train observer able dist guis procedure proficiency improve ment code category also similar modernist roach remarkable success five century reason doubt offer route progress perhaps method solve problem seemingly link method consider study report alberti whose purpose measurement instrument instrument design help collect well understand traffic controller error identify area weakness find possibility improvement method ask observer count primarily rate hour categorize type error use taxonomy propose developer already use pick apart categorize error past incident would real time field set apply pair psychologist traffic controller would study traffic control work go real time observe traffic controller psychologist train taxonomy instruct take note error could despite common indoctrination substantial difference number error group observer note small number error actually observe people watch performance use classify behavior continue worth management exposition totally different count close inspection score sheet reveal traffic controller psychologist tend different subset type available indicate negotiable notion fragment performance mean entirely different thing different similarly train standardized group observer traffic controller rely external working condition interface personnel time resource categorize error whereas psychologist prefer locate somewhere presume quarter mind work memory mental state attention lapse moreover traffic controller actually work could group coder wrong debriefing session expose many observed error error say commit rather normal work expression deliberate strategy intend manage problem foresee situation counter either understand croft report observation cockpit error half error reveal counter never discover flight crew realist argue ability discover error people thing confirm strength superiority method alberti case coder force disavow claim epistemological privilege embrace ontological lativi instead reclassify error normal ion render score sheet virtually devoid count early transfer aircraft example turn corre pond deliberate strategy connect controller foresight plan ahead workload management rather expression weakness strategy uncover source robustness would never come would misrepresent characterize classification normalization action first appear deviant outside critical aspect really understand human work strength weaknesse vaughan without understand process normalization impossible penetrate situate mean error violation classification error crumble inherent weakness naive realism underlie realist idea error exist observe capture document independently observer would mean make difference observe patently presume realism naive observation idea ional influence make possible first place great less extent observe worldview govern observation realism work impossible separate observer observed acknowledge",
      "tokens": 409
    },
    {
      "chunk_id": "ten_questions_about_human_error_3.docx_5",
      "text": "problem international civil aviation organization icao call development human performance collection method rely subjective assessment possible thing objective observation another human behavior presume reality traffic control counting method reveal action classify base appear observer alberti confirm logi lativi sometimes observe entirely controversial take spoiler example chapter flight crew spoiler make mistake apply view human explain context situation mitigate factor explain spoiler spoiler fact occur multiple different observer would agree flight crew fail spoiler acknowledge existence fact stare face fact fact always privilege ruling paradigm fact always favor current interpretation fold exist construct render go fact actually exist virtue current neither discover give meaning without thing observation without paradigm research sence particular worldview impossible word paul bend close analysis find science know bare fact fact enter knowledge already view certain therefore essentially idea ional bend call idea fact available independently objectively favor theory another autonomy principle autonomy principle assert fact available empirical content theory procedural error fact threat model objectively available alternative theory work spoiler example chapter show error occur background case background systemic structural original human pale become transparent normalize become invisible backdrop context procedure time engineering trade weaken hydraulic system omission spoiler dissolve figure ground trade place long really serva interesting deep investigation ground come figure backdrop begin take precedence actual story subsume swallow original long dist shed singular fail decision moment somebody apply naturalistic decision make procedure instead continuous flow action assessment couple mutually cue flow nonlinear feedback loop interaction inextricably embed multi layered evolve context human interac tion system word continuous control task characterization hostile digitization necessary fish human error whether individual error depend theory use objective observation fact observer count participant participate creation serve fact look work course sheer presence counter probably distort people normal practice perhaps turn situated form ance window dress posture fundamentally observer count participant fact would exist without create method observer participant impossible separate observer object make procedure real observe whole point ontological lativi mean autonomy principle false fact stable aspect independent reality reveal scientist wield right instrument method discovery description every fact dependent particular theory word einstein theory determine fact available independent suppose well theory come along account dure error closely match reality stick model scientific progress disprove long follow idea theory dismiss compelling reason compelling reason arise overwhelming number",
      "tokens": 399
    },
    {
      "chunk_id": "ten_questions_about_human_error_3.docx_6",
      "text": "fact disagree theory scientific work idea clean confrontation observe fact theory work fact exist without theory resisting change theory right idea scientific read theoretical progress accumulation observe disagree fact ultimately manage topple theory also work counter instance fact disagree instead observation reveal counter instance error resist unique classification category count method researcher tend match observation theory kuhn puzzle address refinement method counter instance word speak theory accord kuhn define response mati crisis scientist treat anomaly counter instance though extremely difficult people ounce paradigm crisis instead stem logical difficulty suffer counting method cause consequence procedural proficiency dismiss minor irritant reason engage methodological refine ment consonant current paradigm neither scientist support community industry forego paradigm unless viable alternative ready take place among sustained argument surround continuation count researcher engage class cation willing acknowledge perfect go show something well industry concur kuhn point decision reject paradigm necessarily coin cide acceptance another propose viable alternative theory deal fact however exceedingly difficult prove historically bend fact privilege status galileo observation generate observation motivate native explanation place earth universe serva ion favor copernican heliocentric interpretation earth go around geocentric go around earth copernican interpretation however worldview currently accept many doubted gali valid empirical window heliocentric reality people highly suspicious instrument ask galileo open telescope prove little hiding inside otherwise could celestial body closely hide telescope problem offer theoretical explanation could telescope suppose offer well picture naked could relevant theory optic develop generating well like galileo develop entirely method well access telescope little dislodge establish theory allow people phenomenon naked explain similarly people happen naked without help classification method pilot fail spoiler common confirm go around earth earth fix church right galileo wrong observed fact could prove right coherent theory ready accommodate fact give mean church right fact theory deal interestingly church keep close reason define time consider social political ethical implication galileo alternative risky accept certainly ground tentative rickety evidence disavowing geocentric idea would disavow creation remove common ontological nominator past millennium severely undermine authority political power church derive classification meth guard piece rationality people industry would loathe disintegrate",
      "tokens": 389
    },
    {
      "chunk_id": "ten_questions_about_human_error_3.docx_7",
      "text": "error occur dist shed objectively error indication unsafe performance performance performance identifiable cause people perform failure happen without supposedly factual basis without hope objective rationality traditional establish way deal threat safety try create progress could collapse cartesian anxiety would grip industry research community hold people countable mistake error report safety occurrence maintain expensive incident reporting scheme error cause adverse event question broad class appeal lativi postmodernism lativi accord detractor lead moral ambiguity nihilism lack structural progress instead hold realist status observed fact still privilege error exist naive realist argument error exist natural necessary also quite impeccable quite forceful idea exist contrast unnatural absurd within tabl paradigm challenge sheer legitimacy question raise existence error implication legitimacy raise question indeed psychologist would deny existence error altogether pursue doubtful line argument reason hobbs current paradigm judge absurd unnatural question whether error exist worth pursue doubtful unscientific strictest scientific pursuit measure define within rule paradigm precisely scientist succeed bring statement fact close agreement procedure other would discredit scientist rather theory galileo suffer scientist discredit least prevail paradigm gali proceed introduce interpretation unnatural absurd countercultural revolutionary notice fact interpret side bend masterfully describe galileo engage propaganda logical trickery imaginary conversation redo salviati write native tongue rather latin ontological uncertainty epistemological difficulty geocentric interpretation display sheer logic interpretation apart whereas heliocentric interpret tion triumph appeal empirical fact fail fact still force prevail paradigm rather alter native appeal logic still succeed true counting classification imagine conversation error result physiological psychological limit ion human cause include fatigue workload fear cognitive overload interpersonal communication information process flawed decision make redo error case simply result flawed decision making would logic cause categorize error cause decision failure brief failure prioritize attention improper procedure forth redo appear causal explanation simply label whether decision failure prioritize attention still sound like least interpret worldview cause exclusion around error cause decision like ion cause error nothing logic rule tautology explanation argument help either appeal logic fail face overwhelm support ruling",
      "tokens": 359
    },
    {
      "chunk_id": "ten_questions_about_human_error_3.docx_8",
      "text": "paradigm support derive consensus authority political social organ ional imperative rather logical empirical basis pretty porous einstein express amazement common reflex rely measurement count rather logic argument really strange ask letter bear human being normally deaf strong argument always incline overestimate measure curacy bend numbers strong arguments weak counting generate number rely accurate measurement recall croft announce researcher perfect way monitor pilot performance rather argument argument propaganda psychological trickery serve substitute development alternative theory galileo case postmodernist right realist wrong without paradigm without worldview fact people reject theory basis argument logic alone take place paradigmatic interregnum would produce suspend theoretical vacuum researcher would long able fact anything meaningful consider evidence alternative theory like need come superior explanation performance varia ion interpretation sensitive situated form ance attempt capture theory error rather performance variation inherently neutral change adjustment people deal complex dynamic situation theory resist come outside avoid judge people tion external situation look subject inside outline theory develop various place safety absence negatives first though another question people bother count first place goal hope empirical measure help accomplish well way achieve goal final counting help make progress safety put link error safety trial counting negative error anything useful safety quantity error quality manage safety class cation method assume close mapping assume absence reduction error synonymous progress safety treat safety positivist measurable counting breathe scientific spirit bygone human performance laboratory gauge count error still do researcher limit contrived task behavior spartan setting export natural setting people carry complex dynamic interactive work determinant outcome deeply confound matter idea realist count compelling industry reason numerical performance measurement manager easily infatuate balanced scorecard faddish figure performance entire business model depend quantify form ance result quantify safety counting become another quantitative basis managerial intervention pieces operation excised formalize origin convert graph chart subsequently form inspiration intervention allow manager airline elaborate idea control operational practice outcome managerial control however exist purposefully mula ting try influence intention action operational people angell strau control consequence safety ultimately get measure industry wide cause real world complex operational environment stochastic another tricky aspect try create progress safety count classification take context regard count error error accord realist inter preta",
      "tokens": 398
    },
    {
      "chunk_id": "ten_questions_about_human_error_3.docx_9",
      "text": "ion represent kind equivalent category performance failure objective intention matter situation assumption exist wise tabulation become untenable orange apple orange enter method give autonomy principle false counting method apple orange silly statistical tabulation claim doctor time dangerous owner alberti show attempt human capability decision make proficiency liber tion discrete category doom mislead cope complexity actual practice without serious degeneration angell strau classification disembodie remove context help produce behavior particular manifest tion embodiment actually retard understand local ional principle people behavior rational view side situation impossible maintain context remove controversial action categorization move context observation kind tidily lock category objectify formalize situation bring forth without context local rationality without local rationality stand human without understand human learn create progress safety safety reflexive project safety likely measurement management nega ive error error epistemological elusive know know really procedure proficiency ontologically lativi means perform badly inside particular situation different person person notion safety similarly lack objective common denominator idea behind measure safety count safety kind objective stable perhaps ideal reality measure reflect represent method idea hold example propose safety construct human concept other factor begin probe individual practitioner construct safety assess understand risk perceive ability manage challenge situation substantial part practitioner construction safety turn flex assess person competence skill maintain safety across different situation interestingly mismatch tween risk alien critical particular threat safety perceive practitioner frequency encounter often threat safety fact practice safety threat salient one least frequently deal safety akin reflexive project sustain able narrative self identity develop face frequently frequently counter risk something referential something common denominator open type approx mati good method rather safety reflexive something people relate number produce count logical endpoint ural analysis focus suppose cause consequence define risk safety instrumentally term minimize presumably measurable consequence second recent approach socially politically orient place emphasis representation perception interpretation rather structural feature managerial appeal number generate count carry reflexivity nuance work create safety line ultimately determine safety outcome people local ion assessment shape perspective turn embed history ritual interaction belief myth people organization organizational subculture dual would explain objective empirical indicator organizational definition safety difficult",
      "tokens": 378
    },
    {
      "chunk_id": "ten_questions_about_human_error_3.docx_10",
      "text": "obtain opera tor reliable system express evaluation positive state mediate human action evaluation reflexively become part state safety describe word description safety mean individual operator part safety dynamic subjective safety story group organization tell relation task environment measure safety organization capture group story management measure medi reflexive idea count organization order measure safe large recent dent provide clue start look wood main source residual risk otherwise safe transportation system drift failure describe chapter pressures scarcity tion narrow organization focus goal associate production accumulate base empirical success accident safety increasingly trade goal maximize profit capacity utilization organization member little large daily decision begin believe past success guarantee future safety historical success reason conf behavior lead successful outcome next time around absence failure word take evidence hazard present countermeasure already place effective model risk embed deeply reflexive rie safety talk make explicit qualitative investigation probe interpretative aspect situate human assessment action count little luci date qualitative study could reveal currently trade model risk increasingly actual nature hazard though course difficult establish ontologically absolutist presence hazard particular aspect organization member evaluate safety story however serve marker woods example call marker distance differ proc organizational member failure organization relevant situation discard event cause appear surface dissimilar distant discover qualitative inquiry help specify people organization reflexively create idea story safety organ tion section different technical problem different manager differ history claim already address particular safety cern reveal event mean immune problem seemingly divergent event represent similar underlying tern drift towards hazard reliability organization characterize preoccupation failure continually ask thing wrong could go wrong rather congratulate fact thing go right differ mean underplay preoccupation prevent learn event elsewhere throw cle flow safety relate information additional process discover include extent organization resist oversimplify interpretation operational whether defer expertise expert judgment rather manage rial imperative also could interesting probe extent solve process fragment across organizational department section subcontractor accident flammable oxygen generator place aircraft cargo hold without ship cap subsequently burn aircraft relate contractor together make virtual airline hundred people within subcontractor log work part aircraft subcontractor many player network organization company task different aspect run constitute airline relevant maintenance part among ship cap available subcontractor idea expired oxygen canister generate absence central guidance local",
      "tokens": 394
    },
    {
      "chunk_id": "ten_questions_about_human_error_3.docx_11",
      "text": "understanding ship ping cap necessary foggy good work distribute among many participant nobody able anymore picture include regulator nobody able recognize gradual erosion safety constraint design operation original system safety reflexive project rather objective datum human tor researcher must develop entirely probe measure safety health organization count suffice uphold sion rationality control offer neither real insight duct route progress safety course matter debate whether vaguely define organizational process could part safety probe distance differ deference pert fragmentation problem solve incremental judgment aster real error counting method replace augment reality phenomenon beholder observer observe separate object subject largely indistinguishable process phenomena real enough wield theory accommodate result criteria success elsewhere exam measure map past evidence precursor fail mapping subject paradigmatic interpretation evidence base indeed consonant ontological relativity human factor enter debate probably never close doctor dangerous owner error exist depend real issue therefore lie step fray whether count error durkheim fact hand safety reflexive project compete premise practice reflect particular model risk model risk interesting differential ability access empirical truth relative human tor system safety monitoring safety pursue monitor monitoring want make prog safety important step engage meta monitoring become well aware model risk embody assumption approach safety",
      "tokens": 213
    }
  ]
}